awsbw/awsbw.py
awsbw-0.1.5.dist-info/METADATA
awsbw-0.1.5.dist-info/PKG-INFO-MacBook
awsbw-0.1.5.dist-info/RECORD
awsbw-0.1.5.dist-info/WHEEL
awsbw-0.1.5.dist-info/entry_points.txt
awsbw-0.1.5.dist-info/top_level.txt
